jito_geyser/__init__.py
jito_geyser/generated/__init__.py
jito_geyser/generated/confirmed_block_pb2.py
jito_geyser/generated/confirmed_block_pb2.pyi
jito_geyser/generated/confirmed_block_pb2_grpc.py
jito_geyser/generated/confirmed_block_pb2_grpc.pyi
jito_geyser/generated/geyser_pb2.py
jito_geyser/generated/geyser_pb2.pyi
jito_geyser/generated/geyser_pb2_grpc.py
jito_geyser/generated/geyser_pb2_grpc.pyi
jito_geyser/generated/transaction_by_addr_pb2.py
jito_geyser/generated/transaction_by_addr_pb2.pyi
jito_geyser/generated/transaction_by_addr_pb2_grpc.py
jito_geyser/generated/transaction_by_addr_pb2_grpc.pyi
jito_geyser-0.1.0.dist-info/WHEEL
jito_geyser-0.1.0.dist-info/METADATA
jito_geyser-0.1.0.dist-info/RECORD
