Metadata-Version: 2.1
Name: jito-geyser
Version: 0.1.0
Summary: Jito Labs Geyser Client
Author: Jito Labs
Author-email: support@jito.wtf
Requires-Python: >=3.10,<4.0
Classifier: Programming Language :: Python :: 3
Classifier: Programming Language :: Python :: 3.10
Classifier: Programming Language :: Python :: 3.11
Requires-Dist: grpcio (>=1.51.1,<2.0.0)
Requires-Dist: isort (>=5.11.4,<6.0.0)
Requires-Dist: protobuf (>=4.21.12,<5.0.0)
